kaki/__init__.py
kaki/__main__.py
kaki/hotreload.py
kaki/main.py.tmp
kaki/server.py
kaki_cli-1.0.9.dist-info/METADATA
kaki_cli-1.0.9.dist-info/WHEEL
kaki_cli-1.0.9.dist-info/entry_points.txt
kaki_cli-1.0.9.dist-info/RECORD
