Metadata-Version: 2.1
Name: kaki-cli
Version: 1.0.9
Summary: Kivy Hotreload
Home-page: https://github.com/kengoon/kaki
License: MIT
Author: Kenechukwu Akubue
Author-email: kengoon19@gmail.com
Requires-Python: >=3.9,<4.0
Classifier: License :: OSI Approved :: MIT License
Classifier: Programming Language :: Python :: 3
Classifier: Programming Language :: Python :: 3.9
Classifier: Programming Language :: Python :: 3.10
Classifier: Programming Language :: Python :: 3.11
Classifier: Programming Language :: Python :: 3.12
Requires-Dist: buildozer (>=1.5.0,<2.0.0)
Requires-Dist: cython (>=3.0.12,<4.0.0)
Requires-Dist: kivy (>=2.3.1,<3.0.0)
Requires-Dist: psutil (>=7.0.0,<8.0.0)
Requires-Dist: setuptools (>=78.1.0,<79.0.0)
Requires-Dist: watchdog (>=6.0.0,<7.0.0)
Project-URL: Repository, https://github.com/kengoon/kaki
